[
    {
        "moviename":"Prince",
        "imgpath":"https://1847884116.rsc.cdn77.org/telugu/gallery/movies/prince2022/poster.jpg",
        "year":2022
    },
    {
        "moviename":"Liger",
        "imgpath":"https://1847884116.rsc.cdn77.org/telugu/gallery/movies/liger2021/poster.jpg",
        "year":2023
    },
    {
        "moviename":"Gaalodu",
        "imgpath":"https://1847884116.rsc.cdn77.org/telugu/gallery/movies/gaalodu2021/poster.jpg",
        "year":2023
    },
    {
        "moviename":"Dhamaka",
        "imgpath":"https://1847884116.rsc.cdn77.org/telugu/gallery/movies/dhamaka22/poster.jpg",
        "year":2021
    },
    {
        "moviename":"Virupaksha",
        "imgpath":"https://1847884116.rsc.cdn77.org/telugu/gallery/movies/virupaksha22/poster.jpg",
        "year":2020
    },
    {
        "moviename":"Pushpa 2",
        "imgpath":"https://1847884116.rsc.cdn77.org/telugu/gallery/movies/pushpa2/poster01.jpg",
        "year":2024
    },{
        "moviename":"Jailer",
        "imgpath":"https://1847884116.rsc.cdn77.org/telugu/gallery/movies/jailer22/poster.jpg",
        "year":2023
    },
    {
        "moviename":"Rangabali",
        "imgpath":"https://1847884116.rsc.cdn77.org/telugu/gallery/movies/rangabali/rangaposter01.jpg",
        "year":2022
   },
   {
    "moviename":"F3",
    "imgpath":"https://1847884116.rsc.cdn77.org/telugu/gallery/movies/f3_2021/poster.jpg",
    "year":2022
},
{
    "moviename":"RRR",
    "imgpath":"https://1847884116.rsc.cdn77.org/telugu/gallery/movies/rrr2020/poster_rr01.jpg",
    "year":2023
},{
    "moviename":"Krishna Vrinda Vihari",
    "imgpath":"https://1847884116.rsc.cdn77.org/telugu/gallery/movies/krishnavrindavihari2022/poster.jpg",
    "year":2022
},{
    "moviename":"Acharya",
    "imgpath":"https://1847884116.rsc.cdn77.org/telugu/gallery/movies/Acharya2020/poster.jpg",
    "year":2023
},
{
    "moviename":"Sammathame",
    "imgpath":"https://1847884116.rsc.cdn77.org/telugu/gallery/movies/sammathame2021/sammathameposter.jpg",
    "year":2023
},
{
    "moviename":"Bichagadu 2",
    "imgpath":"https://1847884116.rsc.cdn77.org/telugu/gallery/movies/bichagadu2/poster.jpg",
    "year":2021
},{
    "moviename":"Bhola Shanker",
    "imgpath":"https://1847884116.rsc.cdn77.org/telugu/gallery/movies/bholashankar2021/poster02.jpg",
    "year":2023
},
{
    "moviename":"Swathimuthyam",
    "imgpath":"https://1847884116.rsc.cdn77.org/telugu/gallery/movies/swathimuthyam2022/poster.jpg",
    "year":2022
},{
    "moviename":"ThankYou",
    "imgpath":"https://1847884116.rsc.cdn77.org/telugu/gallery/movies/thankyou2022/poster.jpg",
    "year":2021
},
{
    "moviename":"RamaBhanam",
    "imgpath":"https://1847884116.rsc.cdn77.org/telugu/gallery/movies/ramabanam/poster01.jpg",
    "year":2023
},
{
    "moviename":"Prince",
    "imgpath":"https://1847884116.rsc.cdn77.org/telugu/gallery/movies/prince2022/poster.jpg",
    "year":2022
},
{
    "moviename":"Liger",
    "imgpath":"https://1847884116.rsc.cdn77.org/telugu/gallery/movies/liger2021/poster.jpg",
    "year":2023
},{
    "moviename":"Saripodha Sanivarm",
    "imgpath":"https://www.5movierulz.skin/uploads/Saripodhaa-Sanivaaram-Telugu.jpg",
    "year":2023
},
{
    "moviename":"Kill",
    "imgpath":"https://www.5movierulz.skin/uploads/Kill-Telugu.jpg",
    "year":2023
},
{
    "moviename":"Vaazha",
    "imgpath":"https://www.5movierulz.skin/uploads/Vaazha-Biopic-of-a-Billion-Boys-Malayalam.jpg",
    "year":2023
},{
    "moviename":"Thiragabadara Saami",
    "imgpath":"https://www.5movierulz.skin/uploads/Saripodhaa-Sanivaaram-Telugu.jpg",
    "year":2023
},
{
    "moviename":"Thangalaan",
    "imgpath":"https://www.5movierulz.skin/uploads/Thangalaan-Telugu.jpg",
    "year":2023
}
]